philoseismos/__init__.py
philoseismos/dispersion/__init__.py
philoseismos/dispersion/rdc.py
philoseismos/grids/__init__.py
philoseismos/grids/surfer6binary.py
philoseismos/grids/surfer6text.py
philoseismos/models/__init__.py
philoseismos/models/hlm.py
philoseismos/models/layer.py
philoseismos/plotting/__init__.py
philoseismos/plotting/dispersion.py
philoseismos/plotting/imshow.py
philoseismos/plotting/spectra.py
philoseismos/plotting/wiggle.py
philoseismos/processing/__init__.py
philoseismos/processing/spectra.py
philoseismos/segy/__init__.py
philoseismos/segy/bfh.py
philoseismos/segy/constants.py
philoseismos/segy/dm.py
philoseismos/segy/g.py
philoseismos/segy/gfunc.py
philoseismos/segy/segy.py
philoseismos/segy/tfh.py
philoseismos-0.0.32a0.dist-info/LICENSE
philoseismos-0.0.32a0.dist-info/METADATA
philoseismos-0.0.32a0.dist-info/WHEEL
philoseismos-0.0.32a0.dist-info/top_level.txt
philoseismos-0.0.32a0.dist-info/RECORD
