Metadata-Version: 2.1
Name: philoseismos
Version: 0.0.32a0
Summary: Engineering seismologist's toolbox
Home-page: https://github.com/iod-ine/philoseismos
Author: Ivan Dubrovin
Author-email: io.dubrovin@icloud.com
License: UNKNOWN
Platform: UNKNOWN
Classifier: Programming Language :: Python :: 3
Classifier: License :: OSI Approved :: MIT License
Classifier: Operating System :: OS Independent
Classifier: Development Status :: 3 - Alpha
Classifier: Natural Language :: English
Requires-Python: >=3.6
Requires-Dist: numpy
Requires-Dist: pandas
Requires-Dist: scipy
Requires-Dist: matplotlib
